{
  "_class": "shapePath",
  "booleanOperation": -1,
  "clippingMaskMode": 0,
  "do_objectID": "8A4597EE-B8F0-4E0B-B50D-B2A1A3AD3FBF",
  "edited": true,
  "exportOptions": {
    "_class": "exportOptions",
    "do_objectID": "6ED7F33E-CBDB-4787-AE9F-EFA9E091E36B",
    "exportFormats": [
    ],
    "includedLayerIds": [
    ],
    "layerOptions": 0,
    "shouldTrim": false
  },
  "frame": {
    "_class": "rect",
    "constrainProportions": false,
    "do_objectID": "63C8D66F-9758-4323-BEF5-F150A00C6A2A",
    "height": 8.566000000000031,
    "width": 7.179250000000081,
    "x": 8.965750000000014,
    "y": 9.490000000000009
  },
  "hasClippingMask": false,
  "isClosed": true,
  "isFixedToViewport": false,
  "isFlippedHorizontal": false,
  "isFlippedVertical": false,
  "isLocked": false,
  "isVisible": true,
  "layerListExpandedType": 0,
  "name": "Path",
  "nameIsFixed": false,
  "pointRadiusBehaviour": 1,
  "points": [
    {
      "_class": "curvePoint",
      "cornerRadius": 0,
      "curveFrom": "{-0.021415886060521715, 0.46042493579267563}",
      "curveMode": 4,
      "curveTo": "{0.064247658181565151, 0.42446883025915877}",
      "hasCurveFrom": true,
      "hasCurveTo": false,
      "point": "{0.064247658181565151, 0.42446883025915877}"
    },
    {
      "_class": "curvePoint",
      "cornerRadius": 0,
      "curveFrom": "{0.064247658181565151, 0.5682932523931864}",
      "curveMode": 4,
      "curveTo": "{-0.021415886060521715, 0.53233714685968281}",
      "hasCurveFrom": false,
      "hasCurveTo": true,
      "point": "{0.064247658181565151, 0.5682932523931864}"
    },
    {
      "_class": "curvePoint",
      "cornerRadius": 0,
      "curveFrom": "{1, 1}",
      "curveMode": 1,
      "curveTo": "{1, 1}",
      "hasCurveFrom": false,
      "hasCurveTo": false,
      "point": "{1, 1}"
    },
    {
      "_class": "curvePoint",
      "cornerRadius": 0,
      "curveFrom": "{1, 0}",
      "curveMode": 1,
      "curveTo": "{1, 0}",
      "hasCurveFrom": false,
      "hasCurveTo": false,
      "point": "{1, 0}"
    }
  ],
  "resizingConstraint": 63,
  "resizingType": 0,
  "rotation": 0,
  "shouldBreakMaskChain": false,
  "style": {
    "_class": "style",
    "do_objectID": "8E199BCD-B7DC-41B9-8662-FDCBACE2919E",
    "endMarkerType": 0,
    "fills": [
      {
        "_class": "fill",
        "color": {
          "_class": "color",
          "alpha": 1,
          "blue": 0.2998201549053192,
          "green": 0.303960919380188,
          "red": 0.3008416891098022
        },
        "fillType": 0,
        "isEnabled": true,
        "noiseIndex": 0,
        "noiseIntensity": 0,
        "patternFillType": 1,
        "patternTileScale": 1
      }
    ],
    "miterLimit": 10,
    "startMarkerType": 0,
    "windingRule": 1
  }
}