{
  "_class": "shapeGroup",
  "booleanOperation": 0,
  "clippingMaskMode": 0,
  "do_objectID": "513421FB-4408-40D1-8F15-04C344C9FAD1",
  "exportOptions": {
    "_class": "exportOptions",
    "do_objectID": "72CFD0AA-229D-44D6-8ABC-1092428CC39C",
    "exportFormats": [
    ],
    "includedLayerIds": [
    ],
    "layerOptions": 0,
    "shouldTrim": false
  },
  "frame": {
    "_class": "rect",
    "constrainProportions": false,
    "do_objectID": "10E3F679-5ABD-41C3-9096-398C9E83916C",
    "height": 49.11500000000001,
    "width": 29.82500199950368,
    "x": 585.798,
    "y": 66.33899999999994
  },
  "hasClickThrough": false,
  "hasClippingMask": false,
  "isFixedToViewport": false,
  "isFlippedHorizontal": false,
  "isFlippedVertical": false,
  "isLocked": false,
  "isVisible": true,
  "layerListExpandedType": 1,
  "layers": [
    {
      "class": "shapePath",
      "id": "473AEF37-95A4-4B2B-B007-F30EBAFF1680"
    },
    {
      "class": "shapePath",
      "id": "F43A53D3-8A87-428D-A271-2409CF4A3A5A"
    }
  ],
  "name": "Fill 101",
  "nameIsFixed": false,
  "resizingConstraint": 63,
  "resizingType": 0,
  "rotation": 0,
  "shouldBreakMaskChain": false,
  "style": {
    "_class": "style",
    "do_objectID": "229DCBFF-594B-4C16-82E0-9343F7ADA646",
    "endMarkerType": 0,
    "fills": [
      {
        "_class": "fill",
        "color": {
          "_class": "color",
          "alpha": 1,
          "blue": 0.0337897315621376,
          "green": 0.04151976108551025,
          "red": 0.03956039249897003
        },
        "fillType": 0,
        "isEnabled": true,
        "noiseIndex": 0,
        "noiseIntensity": 0,
        "patternFillType": 1,
        "patternTileScale": 1
      }
    ],
    "miterLimit": 10,
    "startMarkerType": 0,
    "windingRule": 1
  },
  "windingRule": 1
}