{
  "_class": "shapePath",
  "booleanOperation": -1,
  "clippingMaskMode": 0,
  "do_objectID": "556E30AB-34DC-459B-ACEA-1AF740844CEF",
  "edited": true,
  "exportOptions": {
    "_class": "exportOptions",
    "exportFormats": [
    ],
    "includedLayerIds": [
    ],
    "layerOptions": 0,
    "shouldTrim": false
  },
  "frame": {
    "_class": "rect",
    "constrainProportions": false,
    "height": 9.697000000000003,
    "width": 14.54600000000005,
    "x": 0,
    "y": 0
  },
  "hasClippingMask": false,
  "isClosed": true,
  "isFixedToViewport": false,
  "isFlippedHorizontal": false,
  "isFlippedVertical": false,
  "isLocked": false,
  "isVisible": true,
  "layerListExpandedType": 0,
  "name": "Path",
  "nameIsFixed": false,
  "pointRadiusBehaviour": 1,
  "points": [
    {
      "_class": "curvePoint",
      "cornerRadius": 0,
      "curveFrom": "{0.66671249828131862, 0}",
      "curveMode": 4,
      "curveTo": "{0.85074934689948845, 0}",
      "hasCurveFrom": false,
      "hasCurveTo": true,
      "point": "{0.66671249828131862, 0}"
    },
    {
      "_class": "curvePoint",
      "cornerRadius": 0,
      "curveFrom": "{0.14925065310051161, 0}",
      "curveMode": 4,
      "curveTo": "{0.33335624914065931, 0}",
      "hasCurveFrom": true,
      "hasCurveTo": false,
      "point": "{0.33335624914065931, 0}"
    },
    {
      "_class": "curvePoint",
      "cornerRadius": 0,
      "curveFrom": "{0, 0.77621944931421927}",
      "curveMode": 2,
      "curveTo": "{0, 0.22388367536351364}",
      "hasCurveFrom": true,
      "hasCurveTo": true,
      "point": "{0, 0.5000515623388665}"
    },
    {
      "_class": "curvePoint",
      "cornerRadius": 0,
      "curveFrom": "{0.33335624914065931, 1}",
      "curveMode": 4,
      "curveTo": "{0.14925065310051161, 1}",
      "hasCurveFrom": false,
      "hasCurveTo": true,
      "point": "{0.33335624914065931, 1}"
    },
    {
      "_class": "curvePoint",
      "cornerRadius": 0,
      "curveFrom": "{0.85074934689948845, 1}",
      "curveMode": 4,
      "curveTo": "{0.66671249828131862, 1}",
      "hasCurveFrom": true,
      "hasCurveTo": false,
      "point": "{0.66671249828131862, 1}"
    },
    {
      "_class": "curvePoint",
      "cornerRadius": 0,
      "curveFrom": "{1, 0.22388367536351364}",
      "curveMode": 2,
      "curveTo": "{1, 0.77621944931421927}",
      "hasCurveFrom": true,
      "hasCurveTo": true,
      "point": "{1, 0.5000515623388665}"
    }
  ],
  "resizingConstraint": 63,
  "resizingType": 0,
  "rotation": 0,
  "shouldBreakMaskChain": false,
  "style": {
    "_class": "style",
    "endMarkerType": 0,
    "fills": [
      {
        "_class": "fill",
        "color": {
          "_class": "color",
          "alpha": 1,
          "blue": 0.0337897315621376,
          "green": 0.04151976108551025,
          "red": 0.03956039249897003
        },
        "fillType": 0,
        "isEnabled": true,
        "noiseIndex": 0,
        "noiseIntensity": 0,
        "patternFillType": 1,
        "patternTileScale": 1
      }
    ],
    "miterLimit": 10,
    "startMarkerType": 0,
    "windingRule": 1
  }
}