{
  "_class": "shapePath",
  "booleanOperation": -1,
  "clippingMaskMode": 0,
  "do_objectID": "6EB19E00-01E1-4D50-9B42-F9B9CF7BAD6F",
  "edited": true,
  "exportOptions": {
    "_class": "exportOptions",
    "do_objectID": "C9DFEC5E-8536-46A3-A1B8-DBBB556639FE",
    "exportFormats": [
    ],
    "includedLayerIds": [
    ],
    "layerOptions": 0,
    "shouldTrim": false
  },
  "frame": {
    "_class": "rect",
    "constrainProportions": false,
    "do_objectID": "27A03635-C4DE-4684-869B-1B3A236F1654",
    "height": 31.36399999999998,
    "width": 18.05700000000002,
    "x": 694.3699999999999,
    "y": 262.826
  },
  "hasClippingMask": false,
  "isClosed": false,
  "isFixedToViewport": false,
  "isFlippedHorizontal": false,
  "isFlippedVertical": false,
  "isLocked": false,
  "isVisible": true,
  "layerListExpandedType": 1,
  "name": "Fill 97",
  "nameIsFixed": false,
  "pointRadiusBehaviour": 1,
  "points": [
    {
      "_class": "curvePoint",
      "cornerRadius": 0,
      "curveFrom": "{0.42327075372431866, 0}",
      "curveMode": 1,
      "curveTo": "{0.42327075372431866, 0}",
      "hasCurveFrom": false,
      "hasCurveTo": false,
      "point": "{0.42327075372431866, 0}"
    },
    {
      "_class": "curvePoint",
      "cornerRadius": 0,
      "curveFrom": "{0, 0}",
      "curveMode": 1,
      "curveTo": "{0, 0}",
      "hasCurveFrom": false,
      "hasCurveTo": false,
      "point": "{0, 0}"
    },
    {
      "_class": "curvePoint",
      "cornerRadius": 0,
      "curveFrom": "{0.58027357811375402, 0.49901160566254193}",
      "curveMode": 1,
      "curveTo": "{0.58027357811375402, 0.49901160566254193}",
      "hasCurveFrom": false,
      "hasCurveTo": false,
      "point": "{0.58027357811375402, 0.49901160566254193}"
    },
    {
      "_class": "curvePoint",
      "cornerRadius": 0,
      "curveFrom": "{0, 1}",
      "curveMode": 1,
      "curveTo": "{0, 1}",
      "hasCurveFrom": false,
      "hasCurveTo": false,
      "point": "{0, 1}"
    },
    {
      "_class": "curvePoint",
      "cornerRadius": 0,
      "curveFrom": "{0.42327075372431866, 1}",
      "curveMode": 1,
      "curveTo": "{0.42327075372431866, 1}",
      "hasCurveFrom": false,
      "hasCurveTo": false,
      "point": "{0.42327075372431866, 1}"
    },
    {
      "_class": "curvePoint",
      "cornerRadius": 0,
      "curveFrom": "{1, 0.49901160566254193}",
      "curveMode": 1,
      "curveTo": "{1, 0.49901160566254193}",
      "hasCurveFrom": false,
      "hasCurveTo": false,
      "point": "{1, 0.49901160566254193}"
    },
    {
      "_class": "curvePoint",
      "cornerRadius": 0,
      "curveFrom": "{0.42327075372431866, 0}",
      "curveMode": 1,
      "curveTo": "{0.42327075372431866, 0}",
      "hasCurveFrom": false,
      "hasCurveTo": false,
      "point": "{0.42327075372431866, 0}"
    }
  ],
  "resizingConstraint": 63,
  "resizingType": 0,
  "rotation": 0,
  "shouldBreakMaskChain": false,
  "style": {
    "_class": "style",
    "do_objectID": "A9706851-E4E8-407C-9B86-07CF29C534E0",
    "endMarkerType": 0,
    "fills": [
      {
        "_class": "fill",
        "color": {
          "_class": "color",
          "alpha": 1,
          "blue": 0.2998201549053192,
          "green": 0.303960919380188,
          "red": 0.3008416891098022
        },
        "fillType": 0,
        "isEnabled": true,
        "noiseIndex": 0,
        "noiseIntensity": 0,
        "patternFillType": 1,
        "patternTileScale": 1
      }
    ],
    "miterLimit": 10,
    "startMarkerType": 0,
    "windingRule": 1
  }
}