{
  "_class": "shapePath",
  "booleanOperation": -1,
  "clippingMaskMode": 0,
  "do_objectID": "44E79C81-63A4-4DDA-B5E2-CA0B4831160A",
  "edited": true,
  "exportOptions": {
    "_class": "exportOptions",
    "do_objectID": "D0096C6B-BC0D-4DA3-B331-72D07745FDB1",
    "exportFormats": [
    ],
    "includedLayerIds": [
    ],
    "layerOptions": 0,
    "shouldTrim": false
  },
  "frame": {
    "_class": "rect",
    "constrainProportions": false,
    "do_objectID": "F6125199-3146-4C0D-8C21-D5F84624ED18",
    "height": 15.65300000000001,
    "width": 21.99700000000001,
    "x": 0,
    "y": 0
  },
  "hasClippingMask": false,
  "isClosed": true,
  "isFixedToViewport": false,
  "isFlippedHorizontal": false,
  "isFlippedVertical": false,
  "isLocked": false,
  "isVisible": true,
  "layerListExpandedType": 0,
  "name": "Path",
  "nameIsFixed": false,
  "pointRadiusBehaviour": 1,
  "points": [
    {
      "_class": "curvePoint",
      "cornerRadius": 0,
      "curveFrom": "{1, 1}",
      "curveMode": 1,
      "curveTo": "{1, 1}",
      "hasCurveFrom": false,
      "hasCurveTo": false,
      "point": "{1, 1}"
    },
    {
      "_class": "curvePoint",
      "cornerRadius": 0,
      "curveFrom": "{1, 0.57880278540854779}",
      "curveMode": 1,
      "curveTo": "{1, 0.57880278540854779}",
      "hasCurveFrom": false,
      "hasCurveTo": false,
      "point": "{1, 0.57880278540854779}"
    },
    {
      "_class": "curvePoint",
      "cornerRadius": 0,
      "curveFrom": "{0.49861344728826579, 0}",
      "curveMode": 1,
      "curveTo": "{0.49861344728826579, 0}",
      "hasCurveFrom": false,
      "hasCurveTo": false,
      "point": "{0.49861344728826579, 0}"
    },
    {
      "_class": "curvePoint",
      "cornerRadius": 0,
      "curveFrom": "{0, 0.57880278540854779}",
      "curveMode": 1,
      "curveTo": "{0, 0.57880278540854779}",
      "hasCurveFrom": false,
      "hasCurveTo": false,
      "point": "{0, 0.57880278540854779}"
    },
    {
      "_class": "curvePoint",
      "cornerRadius": 0,
      "curveFrom": "{0, 1}",
      "curveMode": 1,
      "curveTo": "{0, 1}",
      "hasCurveFrom": false,
      "hasCurveTo": false,
      "point": "{0, 1}"
    },
    {
      "_class": "curvePoint",
      "cornerRadius": 0,
      "curveFrom": "{0.49861344728826579, 0.42126110010860529}",
      "curveMode": 1,
      "curveTo": "{0.49861344728826579, 0.42126110010860529}",
      "hasCurveFrom": false,
      "hasCurveTo": false,
      "point": "{0.49861344728826579, 0.42126110010860529}"
    }
  ],
  "resizingConstraint": 63,
  "resizingType": 0,
  "rotation": 0,
  "shouldBreakMaskChain": false,
  "style": {
    "_class": "style",
    "do_objectID": "2B9443C0-2502-42FF-89C7-03B52C3A82A9",
    "endMarkerType": 0,
    "fills": [
      {
        "_class": "fill",
        "color": {
          "_class": "color",
          "alpha": 1,
          "blue": 0.2998201549053192,
          "green": 0.303960919380188,
          "red": 0.3008416891098022
        },
        "fillType": 0,
        "isEnabled": true,
        "noiseIndex": 0,
        "noiseIntensity": 0,
        "patternFillType": 1,
        "patternTileScale": 1
      }
    ],
    "miterLimit": 10,
    "startMarkerType": 0,
    "windingRule": 1
  }
}